moonqueue/__about__.py
moonqueue/__init__.py
moonqueue/excep.py
moonqueue/redis_queue.py
moonqueue/redis_queue_list.py
moonqueue/redis_queue_set.py
moonqueue-0.3.1.dist-info/LICENSE
moonqueue-0.3.1.dist-info/METADATA
moonqueue-0.3.1.dist-info/WHEEL
moonqueue-0.3.1.dist-info/top_level.txt
moonqueue-0.3.1.dist-info/RECORD
