Metadata-Version: 2.1
Name: moonqueue
Version: 0.3.1
Summary: Queue Implementation with Redis
Home-page: https://github.com/Gatsby-Lee/moonqueue
Author: Gatsby Lee
License: GPL-3.0
Keywords: redis queue interface
Platform: UNKNOWN
Classifier: Development Status :: 5 - Production/Stable
Classifier: Intended Audience :: Developers
Classifier: License :: OSI Approved :: GNU General Public License v3 (GPLv3)
Classifier: Programming Language :: Python
Classifier: Programming Language :: Python :: 3
Classifier: Programming Language :: Python :: 3.6
Classifier: Programming Language :: Python :: 3.7
Classifier: Topic :: Utilities
Requires-Python: >=3.6
Requires-Dist: retry-redis
Provides-Extra: dev
Requires-Dist: pytest ; extra == 'dev'
Requires-Dist: wheel ; extra == 'dev'
Requires-Dist: bpython ; extra == 'dev'
Requires-Dist: flake8 ; extra == 'dev'
Requires-Dist: autopep8 ; extra == 'dev'
Requires-Dist: pylint ; extra == 'dev'
Provides-Extra: test
Requires-Dist: pytest ; extra == 'test'
